{
  "meta": {
    "evidence_version": 1,
    "run_id": "20260322T045508Z",
    "generated_at": "2026-03-22T04:55:08.804Z",
    "source_repo": {
      "full_name": "jj-vcs/jj",
      "url": "https://github.com/jj-vcs/jj"
    },
    "spec_path": "specs/2026-03-22/jj-vcs__jj.json"
  },
  "evidence": [
    {
      "id": "E-RD-001",
      "type": "readme",
      "source_url": "https://github.com/jj-vcs/jj#readme",
      "title": "README (segment 1)",
      "excerpt": "<p><img title=\"jj logo\" src=\"docs/images/jj-logo.svg\" width=\"320\" height=\"320\"></p>",
      "fetched_at": "2026-03-22T04:55:12.497Z",
      "meta": {
        "repo_full_name": "jj-vcs/jj",
        "segment": 1,
        "language": "Rust"
      }
    },
    {
      "id": "E-RD-002",
      "type": "readme",
      "source_url": "https://github.com/jj-vcs/jj#readme",
      "title": "README (segment 2)",
      "excerpt": "[![Release](https://img.shields.io/github/v/release/martinvonz/jj)](https://github.com/jj-vcs/jj/releases) [![Release date](https://img.shields.io/github/release-date/martinvonz/jj)](https://github.com/jj-vcs/jj/releases) <br/> [![License](https://img.shields.io/github/license/martinvonz/jj)](https://github.com/jj-vcs/jj/blob/main/LICENSE) [![Discord](https://img.shields.io/discord/968932220549103686.svg?label=&logo=discord&logoColor=ffffff&color=7389D8&labelColor=6A7EC2)](https://discord.gg/dkmfj3aGQN) [![IRC](https://img.shields.io/badge/irc-%23jujutsu-blue.svg)](https://web.libera.chat/?channel=#jujutsu)",
      "fetched_at": "2026-03-22T04:55:12.497Z",
      "meta": {
        "repo_full_name": "jj-vcs/jj",
        "segment": 2,
        "language": "Rust"
      }
    },
    {
      "id": "E-RD-003",
      "type": "readme",
      "source_url": "https://github.com/jj-vcs/jj#readme",
      "title": "README (segment 3)",
      "excerpt": "**[Homepage] &nbsp;&nbsp;&bull;&nbsp;&nbsp;** **[Installation] &nbsp;&nbsp;&bull;&nbsp;&nbsp;** **[Getting Started] &nbsp;&nbsp;&bull;&nbsp;&nbsp;** **[Development Roadmap] &nbsp;&nbsp;&bull;&nbsp;&nbsp;** **[Contributing](#contributing)**",
      "fetched_at": "2026-03-22T04:55:12.497Z",
      "meta": {
        "repo_full_name": "jj-vcs/jj",
        "segment": 3,
        "language": "Rust"
      }
    },
    {
      "id": "E-RD-004",
      "type": "readme",
      "source_url": "https://github.com/jj-vcs/jj#readme",
      "title": "README (segment 4)",
      "excerpt": "[Homepage]: https://www.jj-vcs.dev [Installation]: https://docs.jj-vcs.dev/latest/install-and-setup [Getting Started]: https://docs.jj-vcs.dev/latest/tutorial [Development Roadmap]: https://docs.jj-vcs.dev/latest/roadmap",
      "fetched_at": "2026-03-22T04:55:12.497Z",
      "meta": {
        "repo_full_name": "jj-vcs/jj",
        "segment": 4,
        "language": "Rust"
      }
    },
    {
      "id": "E-RD-005",
      "type": "readme",
      "source_url": "https://github.com/jj-vcs/jj#readme",
      "title": "README (segment 5)",
      "excerpt": "Jujutsu is a powerful [version control system](https://en.wikipedia.org/wiki/Version_control) for software projects. You use it to get a copy of your code, track changes to the code, and finally publish those changes for others to see and use. It is designed from the ground up to be easy to use—whether you're new or experienced, working on brand new projects alone, or large scale software projects with large histories and teams.",
      "fetched_at": "2026-03-22T04:55:12.497Z",
      "meta": {
        "repo_full_name": "jj-vcs/jj",
        "segment": 5,
        "language": "Rust"
      }
    },
    {
      "id": "E-RD-006",
      "type": "readme",
      "source_url": "https://github.com/jj-vcs/jj#readme",
      "title": "README (segment 6)",
      "excerpt": "Jujutsu is unlike most other systems, because internally it abstracts the user interface and version control algorithms from the *storage systems* used to serve your content. This allows it to serve as a VCS with many possible physical backends, that may have their own data or networking models—like [Mercurial] or [Breezy], or hybrid systems like Google's cloud-based design, [Piper/CitC].",
      "fetched_at": "2026-03-22T04:55:12.497Z",
      "meta": {
        "repo_full_name": "jj-vcs/jj",
        "segment": 6,
        "language": "Rust"
      }
    },
    {
      "id": "E-RD-007",
      "type": "readme",
      "source_url": "https://github.com/jj-vcs/jj#readme",
      "title": "README (segment 7)",
      "excerpt": "[Mercurial]: https://www.mercurial-scm.org/ [Breezy]: https://www.breezy-vcs.org/ [Piper/CitC]: https://youtu.be/W71BTkUbdqE?t=645",
      "fetched_at": "2026-03-22T04:55:12.497Z",
      "meta": {
        "repo_full_name": "jj-vcs/jj",
        "segment": 7,
        "language": "Rust"
      }
    },
    {
      "id": "E-RD-008",
      "type": "readme",
      "source_url": "https://github.com/jj-vcs/jj#readme",
      "title": "README (segment 8)",
      "excerpt": "Today, we use Git repositories as a storage layer to serve and track content, making it **compatible with many of your favorite Git-based tools, right now!** However, note that only commits and files are stored in Git; bookmarks (branches) and other higher-level metadata are stored in custom storage outside of Git. All core developers use Jujutsu to develop Jujutsu, right here on GitHub. But it should hopefully work with your favorite Git forges, too.",
      "fetched_at": "2026-03-22T04:55:12.497Z",
      "meta": {
        "repo_full_name": "jj-vcs/jj",
        "segment": 8,
        "language": "Rust"
      }
    },
    {
      "id": "E-IS-001",
      "type": "issue",
      "source_url": "https://github.com/jj-vcs/jj/issues/9164",
      "title": "FR: More info in combined squash description",
      "excerpt": "FR: More info in combined squash description (state:open)",
      "fetched_at": "2026-03-22T04:55:12.497Z",
      "meta": {
        "repo_full_name": "jj-vcs/jj",
        "number": 9164
      }
    },
    {
      "id": "E-IS-002",
      "type": "issue",
      "source_url": "https://github.com/jj-vcs/jj/issues/9099",
      "title": "Bug: Remote name with whitespace causes a panic",
      "excerpt": "Bug: Remote name with whitespace causes a panic (state:open)",
      "fetched_at": "2026-03-22T04:55:12.497Z",
      "meta": {
        "repo_full_name": "jj-vcs/jj",
        "number": 9099
      }
    },
    {
      "id": "E-RL-001",
      "type": "release",
      "source_url": "https://github.com/jj-vcs/jj/releases",
      "title": "v0.39.0",
      "excerpt": "### About jj is a Git-compatible version control system that is both simple and powerful. See the [installation instructions](https://jj-vcs.github.io/jj/v0.34.0/install-and-setup/) to get started. ### Release highlights * `jj arrange` command brings up a TUI where you can reorder and abandon revisions. [#1531](https://github.com/jj-vcs/jj/issues/1531) * `jj bookmark advance` automatically moves bookmarks forward to a target revision (defaults to `@`) using customization points `revsets.bookmark-advance-from` and `revsets.bookmark-advance-to`. It is heavily inspired by the longstanding community alias `jj tug`. ### Breaking changes * Dropped support for legacy index files written by jj < 0.33. New index files will be created as needed. * The following deprecated config options have been removed: - `core.fsmonitor` - `core.watchman.register-snapshot-trigger` * The deprecated command `jj op undo` has been removed. Use `jj op revert` or `jj undo`/`redo` instead. ### Deprecations * `jj debug snapshot` is deprecated in favor of `jj util snapshot`. Although this was an undocumented command in the first place, it will be removed after 6 months (v0.45.0) to give people time to migrate awa…",
      "fetched_at": "2026-03-22T04:55:12.497Z",
      "meta": {
        "repo_full_name": "jj-vcs/jj",
        "tag_name": "v0.39.0",
        "published_at": "2026-03-04T18:28:43Z"
      }
    },
    {
      "id": "E-RL-002",
      "type": "release",
      "source_url": "https://github.com/jj-vcs/jj/releases",
      "title": "v0.38.0",
      "excerpt": "### About jj is a Git-compatible version control system that is both simple and powerful. See the [installation instructions](https://jj-vcs.github.io/jj/v0.34.0/install-and-setup/) to get started. ### Release highlights * Per-repo and per-workspace config is now stored outside the repo, for security reasons. This is not a breaking change because we automatically migrate legacy repos to this new format. `.jj/repo/config.toml` and `.jj/workspace-config.toml` should no longer be used. ### Breaking changes * The minimum supported `git` command version is now 2.41.0. macOS users will need to either upgrade \"Developer Tools\" to 26 or install Git from e.g. Homebrew. * Deprecated `ui.always-allow-large-revsets` setting and `all:` revset modifier have been removed. * `<name>@<remote>` revset symbols can also be resolved to remote tags. Tags are prioritized ahead of bookmarks. * Legacy placeholder support used for unset `user.name` or `user.email` has been removed. Commits containing these values will now be pushed with `jj git push` without producing an error. * If any side of a conflicted file is missing a terminating newline, then the materialized file in the working copy will no longer…",
      "fetched_at": "2026-03-22T04:55:12.497Z",
      "meta": {
        "repo_full_name": "jj-vcs/jj",
        "tag_name": "v0.38.0",
        "published_at": "2026-02-05T14:42:25Z"
      }
    },
    {
      "id": "E-RL-003",
      "type": "release",
      "source_url": "https://github.com/jj-vcs/jj/releases",
      "title": "v0.37.0",
      "excerpt": "### About jj is a Git-compatible version control system that is both simple and powerful. See the [installation instructions](https://jj-vcs.github.io/jj/v0.34.0/install-and-setup/) to get started. ### Release highlights * A new syntax for referring to hidden and divergent change IDs is available: `xyz/n` where `n` is a number. For instance, `xyz/0` refers to the latest version of `xyz`, while `xyz/1` refers to the previous version of `xyz`. This allows you to perform actions like `jj restore --from xyz/1 --to xyz` to restore `xyz` to its previous contents, if you made a mistake. For divergent changes, the numeric suffix will always be shown in the log, allowing you to disambiguate them in a similar manner. ### Breaking changes * [String patterns](docs/revsets.md#string-patterns) in revsets, command arguments, and configuration are now parsed as globs by default. Use `substring:` or `exact:` prefix as needed. * `remotes.<name>.auto-track-bookmarks` is now parsed the same way they are in revsets and can be combined with logical operators. * `jj bookmark track`/`untrack` now accepts `--remote` argument. If omitted, all remote bookmarks matching the bookmark names will be tracked/unt…",
      "fetched_at": "2026-03-22T04:55:12.497Z",
      "meta": {
        "repo_full_name": "jj-vcs/jj",
        "tag_name": "v0.37.0",
        "published_at": "2026-01-08T02:04:07Z"
      }
    },
    {
      "id": "E-RF-001",
      "type": "root_files",
      "source_url": "https://github.com/jj-vcs/jj",
      "title": "ROOT_FILES",
      "excerpt": ".cargo, .config, .editorconfig, .envrc.recommended, .gitattributes, .github, .gitignore, .watchmanconfig, AUTHORS, CHANGELOG.md, Cargo.lock, Cargo.toml, GOVERNANCE.md, LICENSE, README.md, SECURITY.md, cli, default.nix, demos, deny.toml, docs, flake.lock, flake.nix, lib, mkdocs.yml, pyproject.toml, rustfmt.toml, uv.lock, web",
      "fetched_at": "2026-03-22T04:55:12.497Z",
      "meta": {
        "repo_full_name": "jj-vcs/jj",
        "path": "/"
      }
    }
  ]
}
