{
  "schema_version": 3,
  "app": {
    "name": "Ultraviolet",
    "one_liner": "A set of primitives for manipulating terminal emulators with a focus on terminal user interfaces (TUIs)."
  },
  "screens": [
    {
      "name": "Main Terminal Interface",
      "purpose": "Display and interact with cell-based terminal content using the Cursed Render model.",
      "primary_actions": [
        "Handle user input events",
        "Query terminal dimensions",
        "Render dynamic terminal cells"
      ]
    }
  ],
  "rust_commands": [
    {
      "name": "query_terminal_bounds",
      "purpose": "Retrieve the available width and height of the terminal emulator.",
      "async": true,
      "input": {
        "filters": "json",
        "limit": "int",
        "offset": "int"
      },
      "output": {
        "items": "json",
        "total": "int"
      }
    }
  ],
  "data_model": {
    "tables": [
      {
        "name": "terminal_cells",
        "columns": [
          {
            "name": "char",
            "type": "TEXT"
          },
          {
            "name": "style",
            "type": "JSON"
          },
          {
            "name": "x",
            "type": "INTEGER"
          },
          {
            "name": "y",
            "type": "INTEGER"
          }
        ]
      }
    ]
  },
  "mvp_plan": [
    "week 1: Capture keyboard and mouse events",
    "week 1: Implement basic cell rendering",
    "week 1: Initialize terminal screen buffer"
  ],
  "acceptance_tests": [
    "Application correctly renders styled text in a grid-aligned terminal layout.",
    "Terminal.Bounds() returns accurate available width and height after resize."
  ]
}
