{
  "repo": "marcoturi/react-redux-boilerplate",
  "run_id": "20260401T052742Z",
  "generated_at": "2026-04-01T05:27:42.917Z",
  "stages": [
    {
      "name": "parse",
      "ok": true,
      "stats": {
        "attempt": 0
      }
    },
    {
      "name": "wire_validate",
      "ok": true,
      "stats": {
        "attempt": 0
      }
    },
    {
      "name": "normalize",
      "ok": true,
      "stats": {
        "fixes": 10,
        "warnings": 0
      }
    }
  ],
  "final": {
    "ok": true,
    "attempts_used": 0
  },
  "normalize_report": {
    "fixes": [
      "rule:command_io_enriched:input:pnpm_dev",
      "rule:command_io_enriched:output:pnpm_dev",
      "rule:command_io_enriched:input:pnpm_build",
      "rule:command_io_enriched:output:pnpm_build",
      "rule:command_io_enriched:input:pnpm_test",
      "rule:command_io_enriched:output:pnpm_test",
      "rule:command_io_enriched:input:pnpm_e2e_local",
      "rule:command_io_enriched:output:pnpm_e2e_local",
      "rule:command_io_enriched:input:pnpm_check",
      "rule:command_io_enriched:output:pnpm_check"
    ],
    "warnings": []
  }
}
