{
  "repo": "opensolon/soloncode",
  "run_id": "20260403T050756Z",
  "generated_at": "2026-04-03T05:07:56.083Z",
  "stages": [
    {
      "name": "parse",
      "ok": true,
      "stats": {
        "attempt": 0
      }
    },
    {
      "name": "wire_validate",
      "ok": true,
      "stats": {
        "attempt": 0
      }
    },
    {
      "name": "normalize",
      "ok": true,
      "stats": {
        "fixes": 4,
        "warnings": 0
      }
    }
  ],
  "final": {
    "ok": true,
    "attempts_used": 0
  },
  "normalize_report": {
    "fixes": [
      "rule:command_io_enriched:input:run_soloncode",
      "rule:command_io_enriched:output:run_soloncode",
      "rule:command_io_enriched:input:configure_model",
      "rule:command_io_enriched:output:configure_model"
    ],
    "warnings": []
  }
}
